{
  "subtopic_id": "ecommerce_platforms",
  "subtopic_name": "E-commerce Platforms",
  "mode": "finals",
  "difficulty": "average",
  "questions": [
    {
      "question": "What Shopify language customizes themes?",
      "answer": "Liquid",
      "alternatives": [],
      "explanation": "Liquid is Shopify's templating language."
    },
    {
      "question": "What WooCommerce feature processes payments?",
      "answer": "WooCommerce Payments",
      "alternatives": ["payment gateway"],
      "explanation": "WooCommerce Payments handles transactions."
    },
    {
      "question": "What Magento edition is free?",
      "answer": "Open Source",
      "alternatives": ["Community Edition"],
      "explanation": "Magento Open Source is freely available."
    },
    {
      "question": "What Shopify app marketplace provides extensions?",
      "answer": "App Store",
      "alternatives": ["Shopify App Store"],
      "explanation": "The App Store offers Shopify apps."
    },
    {
      "question": "What manages product variations?",
      "answer": "attributes",
      "alternatives": ["product attributes", "variants"],
      "explanation": "Attributes define product variations."
    },
    {
      "question": "What automates marketing emails?",
      "answer": "email marketing",
      "alternatives": ["automation"],
      "explanation": "Email marketing tools send automated campaigns."
    },
    {
      "question": "What tracks customer behavior?",
      "answer": "analytics",
      "alternatives": [],
      "explanation": "Analytics monitor store performance."
    },
    {
      "question": "What reduces prices temporarily?",
      "answer": "discount",
      "alternatives": ["coupon", "promotion"],
      "explanation": "Discounts offer temporary price reductions."
    },
    {
      "question": "What calculates shipping costs?",
      "answer": "shipping calculator",
      "alternatives": ["shipping rates"],
      "explanation": "Shipping calculators determine delivery costs."
    },
    {
      "question": "What integrates third-party services?",
      "answer": "API",
      "alternatives": ["integration"],
      "explanation": "APIs connect external services to platforms."
    }
  ]
}