{
  "subtopic_id": "hardware_basics",
  "subtopic_name": "Hardware Basics",
  "mode": "finals",
  "difficulty": "easy",
  "questions": [
    {
      "question": "What does CPU stand for?",
      "answer": "Central Processing Unit",
      "alternatives": [],
      "explanation": "CPU is the main processor of computers."
    },
    {
      "question": "What does RAM stand for?",
      "answer": "Random Access Memory",
      "alternatives": [],
      "explanation": "RAM provides temporary data storage."
    },
    {
      "question": "What does GPU stand for?",
      "answer": "Graphics Processing Unit",
      "alternatives": [],
      "explanation": "GPU handles graphics and video rendering."
    },
    {
      "question": "What does HDD stand for?",
      "answer": "Hard Disk Drive",
      "alternatives": [],
      "explanation": "HDD is magnetic storage for data."
    },
    {
      "question": "What does SSD stand for?",
      "answer": "Solid State Drive",
      "alternatives": [],
      "explanation": "SSD uses flash memory for storage."
    },
    {
      "question": "What does PSU stand for?",
      "answer": "Power Supply Unit",
      "alternatives": [],
      "explanation": "PSU provides power to components."
    },
    {
      "question": "What is the main circuit board in a computer?",
      "answer": "motherboard",
      "alternatives": [],
      "explanation": "Motherboards connect all hardware components."
    },
    {
      "question": "What hardware component cools the CPU?",
      "answer": "heat sink",
      "alternatives": ["heatsink", "fan"],
      "explanation": "Heat sinks dissipate processor heat."
    },
    {
      "question": "What device displays computer output?",
      "answer": "monitor",
      "alternatives": ["display", "screen"],
      "explanation": "Monitors show visual information."
    },
    {
      "question": "What stores data permanently in a computer?",
      "answer": "hard drive",
      "alternatives": ["HDD", "SSD", "storage drive"],
      "explanation": "Storage drives retain data when off."
    }
  ]
}