{
  "subtopic_id": "input_output_devices",
  "subtopic_name": "Input/Output Devices",
  "mode": "finals",
  "difficulty": "average",
  "questions": [
    {
      "question": "What pen-like input device draws on screens?",
      "answer": "stylus",
      "alternatives": ["digital pen"],
      "explanation": "Styluses enable precision digital drawing."
    },
    {
      "question": "What gaming input device has buttons and directional controls?",
      "answer": "joystick",
      "alternatives": ["gamepad", "controller"],
      "explanation": "Joysticks control game movements."
    },
    {
      "question": "What printer type uses ink cartridges?",
      "answer": "inkjet",
      "alternatives": ["inkjet printer"],
      "explanation": "Inkjet printers spray liquid ink."
    },
    {
      "question": "What printer type uses toner and heat?",
      "answer": "laser printer",
      "alternatives": ["laser"],
      "explanation": "Laser printers fuse toner to paper."
    },
    {
      "question": "What display technology uses organic compounds?",
      "answer": "OLED",
      "alternatives": ["Organic Light-Emitting Diode"],
      "explanation": "OLED displays provide deep blacks."
    },
    {
      "question": "What device reads barcodes?",
      "answer": "barcode scanner",
      "alternatives": ["scanner"],
      "explanation": "Barcode scanners decode product information."
    },
    {
      "question": "What biometric device scans fingerprints?",
      "answer": "fingerprint scanner",
      "alternatives": ["fingerprint reader"],
      "explanation": "Fingerprint scanners verify identity."
    },
    {
      "question": "What mouse type uses optical sensors?",
      "answer": "optical mouse",
      "alternatives": [],
      "explanation": "Optical mice track movement with light."
    },
    {
      "question": "What headset combines headphones and microphone?",
      "answer": "headset",
      "alternatives": [],
      "explanation": "Headsets enable audio communication."
    },
    {
      "question": "What input device recognizes handwriting?",
      "answer": "graphics tablet",
      "alternatives": ["drawing tablet", "digitizer"],
      "explanation": "Graphics tablets capture pen strokes."
    }
  ]
}